rptree/__init__.py
rptree/__main__.py
rptree/cli.py
rptree/rptree.py
rptree-0.1.1.dist-info/LICENSE
rptree-0.1.1.dist-info/METADATA
rptree-0.1.1.dist-info/WHEEL
rptree-0.1.1.dist-info/entry_points.txt
rptree-0.1.1.dist-info/top_level.txt
rptree-0.1.1.dist-info/RECORD
