Metadata-Version: 2.1
Name: rptree
Version: 0.1.1
Summary: Generate directory tree diagrams for Real Python articles
Home-page: https://github.com/realpython/rptree
Author: Real Python
Author-email: info@realpython.com
Maintainer: Leodanis Pozo Ramos
Maintainer-email: leodanis@realpython.com
License: MIT
Platform: UNKNOWN
Classifier: License :: OSI Approved :: MIT License
Classifier: Programming Language :: Python :: 3
Classifier: Programming Language :: Python :: 3.7
Classifier: Programming Language :: Python :: 3.8
Classifier: Programming Language :: Python :: 3.9
Classifier: Programming Language :: Python :: Implementation :: CPython
